Metadata-Version: 2.1
Name: nr.gitignore
Version: 1.0.0
Summary: .gitignore file parser
Home-page: https://gitlab.niklasrosenstein.com/NiklasRosenstein/python/nr.gitignore
Author: Niklas Rosenstein
Author-email: rosensteinniklas@gmail.com
License: MIT
Platform: UNKNOWN
